rhoPy/__init__.py
rhoPy/rho.py
rhopy-0.0.0.dist-info/entry_points.txt
rhopy-0.0.0.dist-info/LICENSE
rhopy-0.0.0.dist-info/METADATA
rhopy-0.0.0.dist-info/WHEEL
rhopy-0.0.0.dist-info/RECORD
