Metadata-Version: 2.3
Name: rhoPy
Version: 0.0.0
Summary: A (currently) small Python library of statistics functions which are aimed to be more efficient and expansive compared to the default library.
License: Apache-2.0
Keywords: statistics,math
Author: Caleb 136144800+cracker76239@users.noreply.github.com
Requires-Python: >=3.13
Classifier: License :: OSI Approved :: Apache Software License
Classifier: Programming Language :: Python :: 3
Classifier: Programming Language :: Python :: 3.13
